libkvikio/GIT_COMMIT
libkvikio/VERSION
libkvikio/__init__.py
libkvikio/_version.py
libkvikio/load.py
libkvikio/include/BS_thread_pool.hpp
libkvikio/include/BS_thread_pool_utils.hpp
libkvikio/include/kvikio/batch.hpp
libkvikio/include/kvikio/bounce_buffer.hpp
libkvikio/include/kvikio/buffer.hpp
libkvikio/include/kvikio/compat_mode.hpp
libkvikio/include/kvikio/compat_mode_manager.hpp
libkvikio/include/kvikio/defaults.hpp
libkvikio/include/kvikio/error.hpp
libkvikio/include/kvikio/file_handle.hpp
libkvikio/include/kvikio/file_utils.hpp
libkvikio/include/kvikio/hdfs.hpp
libkvikio/include/kvikio/http_status_codes.hpp
libkvikio/include/kvikio/mmap.hpp
libkvikio/include/kvikio/remote_handle.hpp
libkvikio/include/kvikio/stream.hpp
libkvikio/include/kvikio/threadpool_wrapper.hpp
libkvikio/include/kvikio/utils.hpp
libkvikio/include/kvikio/version_config.hpp
libkvikio/include/kvikio/cufile/config.hpp
libkvikio/include/kvikio/cufile/driver.hpp
libkvikio/include/kvikio/detail/env.hpp
libkvikio/include/kvikio/detail/nvtx.hpp
libkvikio/include/kvikio/detail/parallel_operation.hpp
libkvikio/include/kvikio/detail/posix_io.hpp
libkvikio/include/kvikio/detail/remote_handle.hpp
libkvikio/include/kvikio/detail/tls.hpp
libkvikio/include/kvikio/detail/url.hpp
libkvikio/include/kvikio/detail/utils.hpp
libkvikio/include/kvikio/shim/cuda.hpp
libkvikio/include/kvikio/shim/cufile.hpp
libkvikio/include/kvikio/shim/cufile_h_wrapper.hpp
libkvikio/include/kvikio/shim/libcurl.hpp
libkvikio/include/kvikio/shim/utils.hpp
libkvikio/include/nvtx3/nvToolsExt.h
libkvikio/include/nvtx3/nvToolsExtCounters.h
libkvikio/include/nvtx3/nvToolsExtCuda.h
libkvikio/include/nvtx3/nvToolsExtCudaRt.h
libkvikio/include/nvtx3/nvToolsExtMem.h
libkvikio/include/nvtx3/nvToolsExtMemCudaRt.h
libkvikio/include/nvtx3/nvToolsExtOpenCL.h
libkvikio/include/nvtx3/nvToolsExtPayload.h
libkvikio/include/nvtx3/nvToolsExtPayloadHelper.h
libkvikio_cu13-25.12.0.dist-info/METADATA
libkvikio_cu13-25.12.0.dist-info/WHEEL
libkvikio_cu13-25.12.0.dist-info/entry_points.txt
libkvikio_cu13-25.12.0.dist-info/RECORD
libkvikio_cu13-25.12.0.dist-info/licenses/LICENSE
